true50/__init__.py
true50/main.py
true50-0.1.dist-info/DESCRIPTION.rst
true50-0.1.dist-info/entry_points.txt
true50-0.1.dist-info/METADATA
true50-0.1.dist-info/metadata.json
true50-0.1.dist-info/RECORD
true50-0.1.dist-info/top_level.txt
true50-0.1.dist-info/WHEEL
