Metadata-Version: 2.0
Name: true50
Version: 0.1
Summary: Script to open true5050 links
Home-page: https://github.com/Bhullnatik/true50
Author: Jimmy Mayoukou
Author-email: Bhullnatik@gmail.com
License: MIT
Download-URL: https://github.com/Bhullnatik/true50/tarball/0.1
Keywords: true5050,true50,script,utility,FiftyFifty,reddit
Platform: UNKNOWN
Classifier: Development Status :: 4 - Beta
Classifier: Environment :: Console
Classifier: License :: OSI Approved :: Apache Software License
Classifier: Programming Language :: Python
Classifier: Programming Language :: Python :: 2.6
Classifier: Programming Language :: Python :: 2.7
Classifier: Programming Language :: Python :: 3
Classifier: Programming Language :: Python :: 3.2
Classifier: Programming Language :: Python :: 3.3
Classifier: Programming Language :: Python :: 3.4
Requires-Dist: beautifulsoup4
Requires-Dist: requests
